packagebuilder/__init__.py
packagebuilder/__main__.py
packagebuilder/packagebuilder.py
keywind_packagebuilder-0.1.1.dist-info/LICENSE
keywind_packagebuilder-0.1.1.dist-info/METADATA
keywind_packagebuilder-0.1.1.dist-info/WHEEL
keywind_packagebuilder-0.1.1.dist-info/top_level.txt
keywind_packagebuilder-0.1.1.dist-info/RECORD
