Metadata-Version: 2.1
Name: keywind-packagebuilder
Version: 0.1.1
Summary: Installing this package will allow you to build python packages with ease.
Home-page: https://github.com/keywind1207/keywind-packagebuilder
Author: Keywind
Author-email: keywind127@gmail.com
License: UNKNOWN
Project-URL: Bug Tracker, https://github.com/keywind1207/keywind-packagebuilder/issues
Platform: UNKNOWN
Classifier: Programming Language :: Python :: 3
Classifier: License :: OSI Approved :: MIT License
Classifier: Operating System :: OS Independent
Requires-Python: >=3.6
License-File: LICENSE
Requires-Dist: markdown
Requires-Dist: twine
Requires-Dist: build
